README.md
setup.py
bin/get-port
get_port/__about__.py
get_port/__init__.py
get_port/scan.py
get_port.egg-info/PKG-INFO
get_port.egg-info/SOURCES.txt
get_port.egg-info/dependency_links.txt
get_port.egg-info/not-zip-safe
get_port.egg-info/top_level.txt