Metadata-Version: 2.1
Name: get-port
Version: 0.0.5
Summary: Get an available port. Checks first for preferred port in case its available, if not returns random.
Home-page: https://github.com/marinko-peso/get-port/
Author: Marinko Peso
Author-email: marinko.peso@gmail.com
License: MIT
Keywords: get-port get port available socket
Platform: UNKNOWN
Classifier: Intended Audience :: Developers
Classifier: License :: OSI Approved :: MIT License
Classifier: Operating System :: OS Independent
Classifier: Programming Language :: Python
Classifier: Programming Language :: Python :: 2
Classifier: Programming Language :: Python :: 2.7
Classifier: Programming Language :: Python :: 3
Classifier: Programming Language :: Python :: 3.6
